README.md
setup.py
perestroika/__init__.py
perestroika/context.py
perestroika/db_layers.py
perestroika/deserializers.py
perestroika/exceptions.py
perestroika/methods.py
perestroika/resource.py
perestroika/serializers.py
perestroika/utils.py
perestroika/validators.py
perestroika.egg-info/PKG-INFO
perestroika.egg-info/SOURCES.txt
perestroika.egg-info/dependency_links.txt
perestroika.egg-info/requires.txt
perestroika.egg-info/top_level.txt
tests/__init__.py
tests/manage.py
tests/test_validators.py
tests/config/__init__.py
tests/config/settings.py
tests/config/urls.py
tests/config/wsgi.py
tests/test_django/__init__.py
tests/test_django/resources.py
tests/test_django/test_django_app.py
tests/test_django/test_json_app.py
tests/test_django/urls.py