Metadata-Version: 2.1
Name: perestroika
Version: 0.1.31
Summary: Rest lib
Home-page: https://github.com/newmediatech/perestroika
Author: Ruslan Roskoshnyj
Author-email: i.am.yarger@gmail.com
License: LICENSE.txt
Download-URL: https://github.com/newmediatech/perestroika/archive/0.1.31.tar.gz
Keywords: REST
Platform: OS Independent
Classifier: Development Status :: 2 - Pre-Alpha
Classifier: License :: OSI Approved :: MIT License
Classifier: Programming Language :: Python :: 3.7
Classifier: Programming Language :: Python :: 3.8
Classifier: Framework :: Django :: 2.2
Requires-Python: >3.6.0
Provides-Extra: tests
Provides-Extra: docs
